.gitignore
LICENSE
README.md
graph_generator_template.py
pyproject.toml
setup.py
examples/example_3D/graph_generator.py
examples/example_3D/main.py
examples/example_4_differents_subplot/main.py
examples/example_advance_interactive_legend/main.py
examples/example_all_interactive_options/graph_generator.py
examples/example_all_interactive_options/main.py
examples/example_basic/graph_widget.py
examples/example_basic/main.py
examples/example_basic_with_pip_install/main.py
examples/example_big_data/graph_generator.py
examples/example_big_data/main.py
examples/example_compare_hover/graph_generator.py
examples/example_compare_hover/main.py
examples/example_cursor/graph_generator.py
examples/example_cursor/main.py
examples/example_cursor_scatter/graph_generator.py
examples/example_cursor_scatter/graph_widget_scatter.py
examples/example_cursor_scatter/main.py
examples/example_custom_touch_widget/graph_custom_widget.py
examples/example_custom_touch_widget/graph_generator.py
examples/example_custom_touch_widget/line_data.py
examples/example_custom_touch_widget/line_setting.py
examples/example_custom_touch_widget/main.py
examples/example_hover/graph_generator.py
examples/example_hover/main.py
examples/example_interactive_axis/graph_generator.py
examples/example_interactive_axis/main.py
examples/example_interactive_converter/main_converter_in_ipython.py
examples/example_interactive_converter/main_converter_multiple_figure.py
examples/example_kivy_navigation_bar/main.py
examples/example_legend/graph_generator.py
examples/example_legend/main.py
examples/example_legend_horizontal/graph_generator.py
examples/example_legend_horizontal/main.py
examples/example_legend_matplotlib/main.py
examples/example_legend_matpotlib_with_figure_update/main.py
examples/example_live_data/graph_generator.py
examples/example_live_data/main.py
examples/example_live_with_big_data/main.py
examples/example_minmax_option/main.py
examples/example_mplcursors/graph_custom_widget.py
kivy_matplotlib_widget.egg-info/PKG-INFO
kivy_matplotlib_widget.egg-info/SOURCES.txt
kivy_matplotlib_widget.egg-info/dependency_links.txt
kivy_matplotlib_widget.egg-info/requires.txt
kivy_matplotlib_widget.egg-info/top_level.txt
