Metadata-Version: 2.1
Name: kivy_matplotlib_widget
Version: 0.16.0
Summary: A Matplotlib interactive widget for kivy
Home-page: https://github.com/mp-007/kivy_matplotlib_widget
Author: mp-007
Author-email: mp-007 <current.address@unknown.invalid>, T-Dynamos <anshdadwal298@mail.com>
License: MIT License
Project-URL: Homepage, https://github.com/mp-007/kivy_matplotlib_widget
Keywords: android,python3,kivy,matplotlib
Classifier: License :: OSI Approved :: MIT License
Classifier: Programming Language :: Python
Classifier: Programming Language :: Python :: 3
Requires-Python: >=3.7
License-File: LICENSE
Requires-Dist: kivy>=2.0.0
Requires-Dist: matplotlib>=3.5.2
